{
    "0": {
        "precision": 0.6506,
        "recall": 0.6729,
        "f1-score": 0.6616,
        "support": 106
    },
    "1": {
        "precision": 0.6506,
        "recall": 0.6729,
        "f1-score": 0.6616,
        "support": 106
    },
    "accuracy": 0.6506,
    "macro avg": {
        "precision": 0.6506,
        "recall": 0.6729,
        "f1-score": 0.6616,
        "support": 212
    },
    "weighted avg": {
        "precision": 0.6506,
        "recall": 0.6506,
        "f1-score": 0.6616,
        "support": 212
    }
}